pyadept/__init__.py
pyadept/describe_segments.py
pyadept/segment_pattern.py
pyadept/segment_walking_bouts.py
pyadept/sliding_functions.py
pyadept/wrapper_compute_results_wear.py
pyadept/wrapper_identify_walking.py
pyadept-0.2.0.dist-info/METADATA
pyadept-0.2.0.dist-info/WHEEL
pyadept-0.2.0.dist-info/licenses/LICENSE
pyadept-0.2.0.dist-info/RECORD
