Metadata-Version: 2.4
Name: pyadept
Version: 0.2.0
Summary: A python implementation of the ADEPT algorithm.
Project-URL: Repository, https://github.com/actigraph/pyadept
Author-email: Marta Karass <mkaras@hsph.harvard.edu>
Maintainer-email: Ali Neishabouri <ali.neishabouri@theactigraph.com>
License-Expression: GPL-3.0-or-later
License-File: LICENSE
Requires-Python: <3.13,>=3.8.1
Requires-Dist: numpy>=1.20
Requires-Dist: pandas>=1.0.5
